{
  "parent": "minecraft:recipes/root",
  "criteria": {
    "has_the_recipe": {
      "conditions": {
        "recipe": "lavasponge:lavasponge"
      },
      "trigger": "minecraft:recipe_unlocked"
    },
    "lavasponge": {
      "conditions": {
        "items": [
          {
            "items": [
              "minecraft:lava_bucket"
            ]
          },
          {
            "items": [
              "minecraft:sponge"
            ]
          }
        ]
      },
      "trigger": "minecraft:inventory_changed"
    }
  },
  "requirements": [
    [
      "lavasponge",
      "has_the_recipe"
    ]
  ],
  "rewards": {
    "recipes": [
      "lavasponge:lavasponge"
    ]
  }
}